persiansyllablecount/__init__.py
persiansyllablecount/persian_syllable_counter.py
persiansyllablecount-1.0.3.dist-info/METADATA
persiansyllablecount-1.0.3.dist-info/RECORD
persiansyllablecount-1.0.3.dist-info/WHEEL
persiansyllablecount-1.0.3.dist-info/top_level.txt
